chatapp/__init__.py
chatapp/admin.py
chatapp/apps.py
chatapp/consumers.py
chatapp/models.py
chatapp/routing.py
chatapp/urls.py
chatapp/utils.py
chatapp/views.py
chatapp/migrations/0001_initial.py
chatapp/migrations/__init__.py
chatapp/static/django_chatapp/css/client.css
chatapp/static/django_chatapp/css/client.scss
chatapp/static/django_chatapp/css/supporter.css
chatapp/static/django_chatapp/css/supporter.scss
chatapp/static/django_chatapp/font/vazir-medium.ttf
chatapp/static/django_chatapp/font/vazir-medium.woff
chatapp/static/django_chatapp/img/chat-room.png
chatapp/static/django_chatapp/img/close.png
chatapp/static/django_chatapp/img/copy.png
chatapp/static/django_chatapp/img/delete.png
chatapp/static/django_chatapp/img/double-check.png
chatapp/static/django_chatapp/img/edit.png
chatapp/static/django_chatapp/img/emoji.png
chatapp/static/django_chatapp/img/game.png
chatapp/static/django_chatapp/img/gotodown.png
chatapp/static/django_chatapp/img/loader.png
chatapp/static/django_chatapp/img/o.png
chatapp/static/django_chatapp/img/plus.png
chatapp/static/django_chatapp/img/reply.png
chatapp/static/django_chatapp/img/report.png
chatapp/static/django_chatapp/img/send.png
chatapp/static/django_chatapp/img/single-check.png
chatapp/static/django_chatapp/img/supporter.png
chatapp/static/django_chatapp/img/x.png
chatapp/static/django_chatapp/js/client.js
chatapp/static/django_chatapp/js/supporter.js
chatapp/static/django_chatapp/js/vue-i18n.js
chatapp/static/django_chatapp/js/vue3.js
chatapp/static/django_chatapp/song/send.mp3
chatapp/templates/client.html
chatapp/templates/supporter.html
chatapp/templatetags/__init__.py
chatapp/templatetags/chatapp.py
django_chatapp-1.4.dist-info/LICENSE
django_chatapp-1.4.dist-info/METADATA
django_chatapp-1.4.dist-info/WHEEL
django_chatapp-1.4.dist-info/top_level.txt
django_chatapp-1.4.dist-info/RECORD
