Metadata-Version: 2.1
Name: django-chatapp
Version: 1.4
Summary: A flexible Chat Application for open source software society.
Home-page: https://github.com/saeedrezaghazanfari/django-chat-app
Download-URL: https://pypi.org/project/django-chatapp/1.4/
Author: SaeedReza Ghazanfari
Author-email: saeedreza.gh.1397@gmail.com
License: MIT
Keywords: django chat websocket channels asgi vuejs
Platform: any
Classifier: Environment :: Web Environment
Classifier: Framework :: Django
Classifier: Intended Audience :: Developers
Classifier: Operating System :: OS Independent
Classifier: Programming Language :: Python
Classifier: Topic :: Software Development :: Libraries :: Application Frameworks
Classifier: Topic :: Software Development :: Libraries :: Python Modules
Requires-Python: >=3
License-File: LICENSE
Requires-Dist: django
Requires-Dist: channels
Requires-Dist: daphne
